{
    "title": "Event calendar block",
    "status": "prototype",
    "version": "0.0.0",
    "context": {
        "blocks": [
            {
                "heroImage": {
                    "src": "/images/event-calendar-block.png",
                    "alt": ""
                },
                "caption": "1 januari",
                "captionType": "rh-caption-mini--triangle",
                "title": "Event's name",
                "description": "Lorem Ipsum is simply dummy text of the printing and typesetting industry. Lorem Ipsum has been the industry's standard dummy text ever since the 1500s, when an unknown printer."
            },
            {
                "heroImage": {
                    "src": "/images/event-calendar-block.png",
                    "alt": ""
                },
                "caption": "30 december",
                "captionType": "rh-caption-mini--triangle",
                "title": "Event's name",
                "description": "Lorem Ipsum is simply dummy text of the printing and typesetting industry."
            },
            {
                "heroImage": {
                    "src": "/images/event-calendar-block.png",
                    "alt": ""
                },
                "caption": "3 mars",
                "captionType": "rh-caption-mini--square rh-caption-mini--right-top",
                "title": "Event's name",
                "description": "Lorem Ipsum is simply dummy text of the printing and typesetting industry. Lorem Ipsum has been the industry's standard dummy text ever since the 1500s."
            },
            {
                "heroImage": {
                    "src": "/images/event-calendar-block.png",
                    "alt": ""
                },
                "caption": "3 mars",
                "captionType": "rh-caption-mini--round rh-caption-mini--right-bottom",
                "title": "Event's name",
                "description": "Lorem Ipsum is simply dummy text of the printing and typesetting industry. Lorem Ipsum has been the industry's standard dummy text ever since the 1500s, when an unknown printer took a galley of type and scrambled it to make a type specimen book."
            },
            {
                "heroImage": {
                    "src": "/images/event-calendar-block.png",
                    "alt": ""
                },
                "caption": "3 mars",
                "captionType": "rh-caption-mini--round rh-caption-mini--left-top",
                "title": "Event's name",
                "description": "Lorem Ipsum is simply dummy text of the printing and typesetting industry. Lorem Ipsum has been the industry's standard."
            },
            {
                "heroImage": {
                    "src": "/images/event-calendar-block.png",
                    "alt": ""
                },
                "caption": "30 december",
                "captionType": "rh-caption-mini--under-image",
                "title": "Event's name",
                "description": "Lorem Ipsum is simply dummy text of the printing and typesetting industry. Lorem Ipsum has been the industry's standard dummy text ever since the 1500s, when an unknown printer took a galley of type and scrambled it to make a type specimen book."
            }
        ]
    }
}